sinesp_client/__init__.py
sinesp_client/body.xml
sinesp_client-1.14.dist-info/METADATA
sinesp_client-1.14.dist-info/WHEEL
sinesp_client-1.14.dist-info/top_level.txt
sinesp_client-1.14.dist-info/RECORD
