Metadata-Version: 2.1
Name: sinesp-client
Version: 1.14
Summary: SINESP Cidadão database client.
Home-page: https://github.com/victor-torres/sinesp-client
Author: Victor Torres
Author-email: vpaivatorres@gmail.com
License: Copyright
Platform: UNKNOWN
Requires-Dist: requests (==2.20.0)
